[
  {
    "url": "https://fr.wikipedia.org/wiki/Apprentissage_automatique",
    "timestamp": "20250710_113110",
    "content_length": 392462
  },
  {
    "url": "https://cy.wikipedia.org/wiki/Dysgu_peirianyddol",
    "timestamp": "20250710_113110",
    "content_length": 86345
  },
  {
    "url": "https://tl.wikipedia.org/wiki/Unang_Pahina",
    "timestamp": "20250710_113110",
    "content_length": 227751
  },
  {
    "url": "https://kn.wikipedia.org/wiki/%E0%B2%AF%E0%B2%82%E0%B2%A4%E0%B3%8D%E0%B2%B0_%E0%B2%95%E0%B2%B2%E0%B2%BF%E0%B2%95%E0%B3%86",
    "timestamp": "20250710_113110",
    "content_length": 169896
  },
  {
    "url": "https://ko.wikipedia.org/wiki/%EC%9C%84%ED%82%A4%EB%B0%B1%EA%B3%BC:%EB%8F%84%EC%9B%80%EB%A7%90",
    "timestamp": "20250710_113110",
    "content_length": 139454
  },
  {
    "url": "https://bs.wikipedia.org/wiki/Wikipedia:Portal",
    "timestamp": "20250710_113110",
    "content_length": 105141
  },
  {
    "url": "https://tl.wikipedia.org/wiki/Wikipedia:Tingnan_ang_buod",
    "timestamp": "20250710_113110",
    "content_length": 76347
  },
  {
    "url": "https://ko.wikipedia.org/wiki/%EC%95%99%EC%83%81%EB%B8%94_%ED%95%99%EC%8A%B5%EB%B2%95",
    "timestamp": "20250710_113110",
    "content_length": 134987
  },
  {
    "url": "https://ko.wikipedia.org/wiki/%EC%9C%84%ED%82%A4%EB%B0%B1%EA%B3%BC:%EC%B6%9C%EC%B2%98_%EB%B0%9D%ED%9E%88%EA%B8%B0",
    "timestamp": "20250710_113110",
    "content_length": 141406
  },
  {
    "url": "https://arxiv.org/search/?searchtype=author&amp;amp%3Bquery=Sondermann%2C+M",
    "timestamp": "20250710_113110",
    "content_length": 17799
  },
  {
    "url": "https://sr.wikipedia.org/wiki/Speech_recognition",
    "timestamp": "20250710_113110",
    "content_length": 173204
  },
  {
    "url": "https://sr.wikipedia.org/wiki/%D0%92%D0%B8%D0%BA%D0%B8%D0%BF%D0%B5%D0%B4%D0%B8%D1%98%D0%B0:%D0%A1%D0%B0%D0%B4%D1%80%D0%B6%D0%B0%D1%98",
    "timestamp": "20250710_113110",
    "content_length": 172237
  },
  {
    "url": "https://pa.wikipedia.org/wiki/%E0%A8%AE%E0%A8%B8%E0%A8%BC%E0%A9%80%E0%A8%A8_%E0%A8%B2%E0%A8%B0%E0%A8%A8%E0%A8%BF%E0%A9%B0%E0%A8%97",
    "timestamp": "20250710_113110",
    "content_length": 103224
  },
  {
    "url": "https://arxiv.org/search/?searchtype=author&amp;amp%3Bquery=Krishnamoorthy%2C+R",
    "timestamp": "20250710_113110",
    "content_length": 17799
  },
  {
    "url": "https://github.com/trending/javascript?spoken_language_code=pa",
    "timestamp": "20250710_113110",
    "content_length": 455905
  },
  {
    "url": "https://eo.wikipedia.org/wiki/Speciala%C4%B5o:Hazarda_pa%C4%9Do",
    "timestamp": "20250710_113110",
    "content_length": 52247
  },
  {
    "url": "https://github.com/arXiv/arxiv-docs/issues",
    "timestamp": "20250710_113110",
    "content_length": 195492
  },
  {
    "url": "https://ceb.wikipedia.org/wiki/Python_(programming_language)",
    "timestamp": "20250710_113110",
    "content_length": 96833
  },
  {
    "url": "https://ml.wikipedia.org/wiki",
    "timestamp": "20250710_113110",
    "content_length": 235830
  },
  {
    "url": "https://nl.wikipedia.org/wiki",
    "timestamp": "20250710_113110",
    "content_length": 222860
  },
  {
    "url": "https://nn.wikipedia.org/wiki",
    "timestamp": "20250710_113110",
    "content_length": 211219
  },
  {
    "url": "https://nl.wikipedia.org/wiki/Portaal:Hulp_en_beheer",
    "timestamp": "20250710_113110",
    "content_length": 144982
  },
  {
    "url": "https://sr.wikipedia.org/wiki/Machine_code",
    "timestamp": "20250710_113110",
    "content_length": 157213
  },
  {
    "url": "https://en.wikipedia.org/wiki/User_talk:Gymkhanapk",
    "timestamp": "20250710_113110",
    "content_length": 55895
  },
  {
    "url": "https://github.com/trending/python?spoken_language_code=ay",
    "timestamp": "20250710_113110",
    "content_length": 455067
  }
]