[
  {
    "url": "https://foundation.wikimedia.org/wiki/Home",
    "timestamp": "20250710_115718",
    "content_length": 238892
  },
  {
    "url": "https://ml.wikipedia.org/w/index.php?title=%E0%B4%AA%E0%B5%8D%E0%B4%B0%E0%B4%A7%E0%B4%BE%E0%B4%A8_%E0%B4%A4%E0%B4%BE%E0%B5%BE&amp;action=info",
    "timestamp": "20250710_115718",
    "content_length": 236206
  },
  {
    "url": "https://et.wikipedia.org/wiki/Informaatika",
    "timestamp": "20250710_115718",
    "content_length": 139833
  },
  {
    "url": "https://wikidata.org/wiki/Special:EntityPage/Q45842",
    "timestamp": "20250710_115718",
    "content_length": 148789
  },
  {
    "url": "https://ru.wikipedia.org/wiki/MIT_Press",
    "timestamp": "20250710_115718",
    "content_length": 91744
  },
  {
    "url": "https://en.wikinews.org/wiki",
    "timestamp": "20250710_115718",
    "content_length": 115473
  },
  {
    "url": "https://lij.wikipedia.org/wiki/Agi%C3%BBtto:Go%C3%ACdda_fondament%C3%A2le",
    "timestamp": "20250710_115718",
    "content_length": 56014
  },
  {
    "url": "https://ba.wikipedia.org/wiki/%D0%98%D0%BD%D1%82%D0%B5%D1%80%D0%BD%D0%B5%D1%82",
    "timestamp": "20250710_115718",
    "content_length": 252451
  },
  {
    "url": "https://simple.wikipedia.org/wiki/Special:Contribute",
    "timestamp": "20250710_115718",
    "content_length": 35360
  },
  {
    "url": "https://en.wikivoyage.org/wiki/Wikivoyage:Help",
    "timestamp": "20250710_115718",
    "content_length": 72060
  },
  {
    "url": "https://fr.wikipedia.org/wiki/Aide:D%C3%A9buter",
    "timestamp": "20250710_115718",
    "content_length": 79002
  },
  {
    "url": "https://hr.wikipedia.org/wiki/JavaScript",
    "timestamp": "20250710_115718",
    "content_length": 88756
  },
  {
    "url": "https://github.com/jrzaurin/pytorch-widedeep/issues",
    "timestamp": "20250710_115718",
    "content_length": 220461
  },
  {
    "url": "https://pa.wikipedia.org/wiki/%E0%A8%B5%E0%A8%B0%E0%A8%B2%E0%A8%A1_%E0%A8%B5%E0%A8%BE%E0%A8%88%E0%A8%A1_%E0%A8%B5%E0%A9%88%E0%A9%B1%E0%A8%AC",
    "timestamp": "20250710_115718",
    "content_length": 152313
  },
  {
    "url": "https://na.wikipedia.org/wiki/Wikipedia:Community_Portal",
    "timestamp": "20250710_115718",
    "content_length": 176094
  },
  {
    "url": "https://github.com/topics/machine-translation",
    "timestamp": "20250710_115718",
    "content_length": 495680
  },
  {
    "url": "https://ru.wikipedia.org/wiki",
    "timestamp": "20250710_115718",
    "content_length": 160997
  },
  {
    "url": "https://fr.wikipedia.org/w/index.php?title=Apprentissage_automatique&amp;action=edit",
    "timestamp": "20250710_115718",
    "content_length": 392726
  },
  {
    "url": "https://es.wikipedia.org/wiki/Especial:CambiosEnEnlazadas/Wikipedia:Portada",
    "timestamp": "20250710_115718",
    "content_length": 226237
  },
  {
    "url": "https://pl.wikipedia.org/wiki/Wikipedia:Portal_wikipedyst%C3%B3w",
    "timestamp": "20250710_115718",
    "content_length": 446245
  },
  {
    "url": "https://ko.wikipedia.org/w/index.php?title=%ED%86%B5%EA%B3%84%EC%A0%81_%EB%B6%84%EB%A5%98&amp;printable=yes",
    "timestamp": "20250710_115718",
    "content_length": 136526
  },
  {
    "url": "https://donate.wikimedia.org/?wmf_source=donate&amp;wmf_medium=sidebar&amp;wmf_campaign=pa.wikipedia.org&amp;uselang=pa",
    "timestamp": "20250710_115718",
    "content_length": 57047
  },
  {
    "url": "https://he.wikipedia.org/wiki/%D7%90%D7%99%D7%A0%D7%98%D7%A8%D7%A0%D7%98",
    "timestamp": "20250710_115718",
    "content_length": 280374
  },
  {
    "url": "https://rw.wikipedia.org/wiki/Wikipedia:Community_Portal",
    "timestamp": "20250710_115718",
    "content_length": 2047262
  },
  {
    "url": "https://gan.wikipedia.org/wiki/Wikipedia:%E7%A4%BE%E5%8D%80",
    "timestamp": "20250710_115718",
    "content_length": 150958
  }
]